{
  "parent": "minecraft:recipes/root",
  "criteria": {
    "has_salmon_steak": {
      "conditions": {
        "items": [
          {
            "items": [
              "lotr:salmon_steak"
            ]
          }
        ]
      },
      "trigger": "minecraft:inventory_changed"
    },
    "has_the_recipe": {
      "conditions": {
        "recipe": "lotr:cooked_salmon_steak_from_smoking"
      },
      "trigger": "minecraft:recipe_unlocked"
    }
  },
  "requirements": [
    [
      "has_salmon_steak",
      "has_the_recipe"
    ]
  ],
  "rewards": {
    "recipes": [
      "lotr:cooked_salmon_steak_from_smoking"
    ]
  }
}